Metadata-Version: 2.1
Name: odoo14-addon-l10n_it_fatturapa_out_rc
Version: 14.0.1.4.1
Summary: Integrazione l10n_it_fatturapa_out e l10n_it_reverse_charge
Home-page: https://github.com/OCA/l10n-italy
Author: TAKOBI, Odoo Community Association (OCA)
Author-email: support@odoo-community.org
License: AGPL-3
Classifier: Programming Language :: Python
Classifier: Framework :: Odoo
Classifier: Framework :: Odoo :: 14.0
Classifier: License :: OSI Approved :: GNU Affero General Public License v3
Classifier: Development Status :: 4 - Beta
Requires-Python: >=3.6
Requires-Dist: odoo14-addon-l10n-it-fatturapa-in
Requires-Dist: odoo14-addon-l10n-it-fatturapa-out
Requires-Dist: odoo14-addon-l10n-it-reverse-charge
Requires-Dist: odoo<14.1dev,>=14.0a
